franklin_educator/__init__.py
franklin_educator/git.py
franklin_educator/data/admin/kasper_token.enc
franklin_educator-0.3.147.dist-info/licenses/LICENSE
franklin_educator-0.3.147.dist-info/METADATA
franklin_educator-0.3.147.dist-info/WHEEL
franklin_educator-0.3.147.dist-info/entry_points.txt
franklin_educator-0.3.147.dist-info/top_level.txt
franklin_educator-0.3.147.dist-info/RECORD
