Metadata-Version: 2.4
Name: franklin-educator
Version: 0.3.147
Summary: Educator plugin for Franklin - adds exercise management commands
Author-email: Kasper Munch <kaspermunch@birc.au.dk>
Maintainer-email: Kasper Munch <kaspermunch@birc.au.dk>
Project-URL: Homepage, https://munch-group.org/franklin-educator
Project-URL: Documentation, https://munch-group.org/franklin
Project-URL: Repository, https://github.com/munch-group/franklin-educator.git
Project-URL: Issues, https://github.com/munch-group/franklin-educator/issues
Keywords: teaching,jupyter,docker,gitlab
Classifier: Development Status :: 4 - Beta
Classifier: Intended Audience :: Education
Classifier: Topic :: Software Development :: Build Tools
Classifier: Programming Language :: Python :: 3
Classifier: Programming Language :: Python :: 3.9
Classifier: Programming Language :: Python :: 3.10
Classifier: Programming Language :: Python :: 3.11
Classifier: Programming Language :: Python :: 3.12
Classifier: Programming Language :: Python :: 3.13
Requires-Python: >=3.9
License-File: LICENSE
Requires-Dist: franklin-cli>=0.24
Dynamic: license-file
